[
  {
    "name": "prod",
    "terraform": {
      "gateway_url": {
        "sensitive": false,
        "type": "string",
        "value": "https://k14ggwft37.execute-api.us-west-2.amazonaws.com"
      },
      "public_files_bucket": {
        "sensitive": false,
        "type": "string",
        "value": "server-side-rendering-1703653603735.te-public-files-6ee549a4"
      },
      "static_files_bucket": {
        "sensitive": false,
        "type": "string",
        "value": "server-side-rendering-1703653603735.te-static-files-6ee549a4"
      }
    }
  }
]