[
  {
    "name": "prod",
    "terraform": {
      "gateway_url": {
        "sensitive": false,
        "type": "string",
        "value": "https://8bbh9tkpld.execute-api.us-west-2.amazonaws.com"
      },
      "public_files_bucket": {
        "sensitive": false,
        "type": "string",
        "value": "server-side-rendering-1670041489493.te-public-files-fa28d7c8"
      },
      "static_files_bucket": {
        "sensitive": false,
        "type": "string",
        "value": "server-side-rendering-1670041489493.te-static-files-fa28d7c8"
      }
    }
  }
]